extraction_triangle/__init__.py
extraction_triangle/coordinates.py
extraction_triangle/triangle_plot.py
extraction_triangle/utils.py
extraction_triangle-0.1.0.dist-info/licenses/LICENSE
tests/__init__.py
tests/test_extraction_triangle.py
extraction_triangle-0.1.0.dist-info/METADATA
extraction_triangle-0.1.0.dist-info/WHEEL
extraction_triangle-0.1.0.dist-info/top_level.txt
extraction_triangle-0.1.0.dist-info/RECORD
